src/__init__.py
src/api.py
src/models.py
src/utils.py
itau_uy_api-0.6.0.dist-info/METADATA
itau_uy_api-0.6.0.dist-info/WHEEL
itau_uy_api-0.6.0.dist-info/licenses/LICENSE
itau_uy_api-0.6.0.dist-info/RECORD
