Metadata-Version: 2.3
Name: itau_uy_api
Version: 0.6.0
Summary: A Python library for interacting with the Itaú UY bank API
Project-URL: Homepage, https://github.com/avitretiak/itau-uy-api
Project-URL: Bug Tracker, https://github.com/avitretiak/itau-uy-api/issues
Project-URL: Repository, https://github.com/avitretiak/itau-uy-api
Author: Avi Tretiak
License-Expression: MIT
License-File: LICENSE
Classifier: Development Status :: 3 - Alpha
Classifier: Intended Audience :: Developers
Classifier: License :: OSI Approved :: MIT License
Classifier: Operating System :: OS Independent
Classifier: Programming Language :: Python :: 3.12
Classifier: Topic :: Office/Business :: Financial
Classifier: Topic :: Software Development :: Libraries :: Python Modules
Requires-Python: >=3.12
Requires-Dist: beautifulsoup4>=4.12.3
Requires-Dist: python-dotenv>=1.0.1
Requires-Dist: requests>=2.32.3
Requires-Dist: ua-generator>=1.0.3
